LICENSE
MANIFEST.in
README.md
package.json
setup.py
dash_dthree/PolyLineAnimate.py
dash_dthree/__init__.py
dash_dthree/_imports_.py
dash_dthree/dash_dthree.min.js
dash_dthree/dash_dthree.min.js.map
dash_dthree/metadata.json
dash_dthree/package-info.json
dash_dthree.egg-info/PKG-INFO
dash_dthree.egg-info/SOURCES.txt
dash_dthree.egg-info/dependency_links.txt
dash_dthree.egg-info/top_level.txt